{
    "object_id": 15957,
    "components": {
        "2": 14649,
        "11": 7362
    },
    "item_info": {
        "name": "Ninjago Spear on ninja hood Proxy",
        "displayName": "Spear Proxy Ninjago",
        "type": "Loot",
        "description": "Spear Proxy Ninjago",
        "internalNotes": "Spear ninja hood Proxy"
    },
    "skills": [],
    "stats": {
        "life": 0,
        "armor": 0,
        "imagination": 0
    },
    "preconditions": {},
    "rarity": 4,
    "is_weapon": 0,
    "is_two_handed": 0,
    "level_requirement": 0,
    "equip_locations": [
        "Consumable"
    ],
    "sell_price": 0,
    "buy_price": 0,
    "alt_currency_type": 0,
    "alt_currency_cost": 0,
    "commendation_currency_type": 0,
    "commendation_currency_cost": 0,
    "stack_size": 1,
    "overview": {},
    "is_sold": 0,
    "is_earned": 0,
    "is_dropped": 0
}