{
    "object_id": 9623,
    "components": {
        "2": 9468,
        "9": 0,
        "11": 4646
    },
    "item_info": {
        "name": "Sentinel Faction Consumable 1",
        "displayName": "Sentinel Super Soda",
        "type": "Loot",
        "description": "Double-click to use!",
        "internalNotes": "Faction Consumable - 8 LP, 10 AP, 16 IP"
    },
    "skills": [
        {
            "imagination_cost": 0,
            "cooldown": 30.0,
            "cooldown_group": 28,
            "name": "Replenish Minifigure",
            "full_description": "Restores 8 Life, 10 Armor, and 16 Imagination"
        }
    ],
    "stats": {
        "life": 0,
        "armor": 0,
        "imagination": 0
    },
    "preconditions": {
        "211": "You must be Level 6 or greater to use this item.",
        "39": "You need to be a member of the Sentinel Faction to use this."
    },
    "rarity": 2,
    "is_weapon": 0,
    "is_two_handed": 0,
    "level_requirement": "6",
    "equip_locations": [
        "Consumable"
    ],
    "sell_price": 10,
    "buy_price": 100,
    "alt_currency_type": 8319,
    "alt_currency_cost": 1,
    "commendation_currency_type": 0,
    "commendation_currency_cost": 0,
    "stack_size": 10,
    "overview": {},
    "is_sold": 1,
    "vendors": [
        {
            "id": 6631,
            "name": "Xeno Blueblade - Sentinel Vendor"
        },
        {
            "id": 12215,
            "name": "Heimlich Stewblaster - Supplies Vendor"
        }
    ],
    "is_earned": 0,
    "is_dropped": 0
}