{
    "object_id": 12619,
    "components": {
        "2": 12409,
        "9": 0,
        "11": 6189
    },
    "item_info": {
        "name": "TEST",
        "displayName": "TEST",
        "type": "Loot",
        "description": null,
        "internalNotes": "Testing Eng Valiant offhand skill"
    },
    "skills": [
        {
            "imagination_cost": 8,
            "cooldown": 45.0,
            "cooldown_group": 24,
            "name": "Create Bot",
            "full_description": "%(DamageCombo) 3 %(Description)Creates a Bot Quick Build that assists you in battle",
            "damage_combo": " 3 ",
            "description": "Creates a Bot Quick Build that assists you in battle"
        }
    ],
    "stats": {
        "life": 0,
        "armor": 0,
        "imagination": 0
    },
    "preconditions": {},
    "rarity": 3,
    "is_weapon": 0,
    "is_two_handed": 0,
    "level_requirement": 0,
    "equip_locations": [
        "Left Hand"
    ],
    "sell_price": 70,
    "buy_price": 700,
    "alt_currency_type": 0,
    "alt_currency_cost": 0,
    "commendation_currency_type": 0,
    "commendation_currency_cost": 0,
    "stack_size": 1,
    "overview": {
        "21054": {
            "hasChargeUp": false,
            "spawnsObject": false,
            "spawnsQuickbuild": true,
            "meleeAttack": false,
            "projectileAttack": false,
            "projectileAttackChargeUp": false,
            "damageComboArray": [],
            "chargeUpArmorRestore": [],
            "chargeUpImaginationRestore": [],
            "projectileLOTs": [],
            "projectileInfo": {},
            "projectileDamageComboArray": [],
            "chargeUpCombo": 0,
            "allDamage": [],
            "attackTypes": []
        }
    },
    "is_sold": 0,
    "is_earned": 0,
    "is_dropped": 0
}