{
    "object_id": 12772,
    "components": {
        "2": 12562,
        "9": 0,
        "11": 6320
    },
    "item_info": {
        "name": "Banana-Wrang",
        "displayName": "Banana-Wrang",
        "type": "Loot",
        "description": null,
        "internalNotes": "3 Damage AOE and Knockdown"
    },
    "skills": [
        {
            "imagination_cost": 3,
            "cooldown": 10.0,
            "cooldown_group": 2,
            "name": "Banana Toss",
            "full_description": "Tosses a banana that does 3 damage and knocks down enemies"
        }
    ],
    "stats": {
        "life": 0,
        "armor": 0,
        "imagination": 0
    },
    "preconditions": {
        "248": "You must be Level 10 or greater to use this item."
    },
    "rarity": 2,
    "is_weapon": 0,
    "is_two_handed": 0,
    "level_requirement": "10",
    "equip_locations": [
        "Left Hand"
    ],
    "sell_price": 482,
    "buy_price": 4825,
    "alt_currency_type": 0,
    "alt_currency_cost": 0,
    "commendation_currency_type": 0,
    "commendation_currency_cost": 0,
    "stack_size": 1,
    "overview": {
        "24651": {
            "hasChargeUp": false,
            "spawnsObject": false,
            "spawnsQuickbuild": false,
            "meleeAttack": true,
            "projectileAttack": false,
            "projectileAttackChargeUp": false,
            "damageComboArray": [
                3
            ],
            "chargeUpArmorRestore": [],
            "chargeUpImaginationRestore": [],
            "projectileLOTs": [],
            "projectileInfo": {},
            "projectileDamageComboArray": [],
            "chargeUpCombo": 0,
            "allDamage": [
                3
            ],
            "attackTypes": [
                "Area of Effect",
                "Interruption"
            ]
        }
    },
    "is_sold": 1,
    "vendors": [
        {
            "id": 12215,
            "name": "Heimlich Stewblaster - Supplies Vendor"
        }
    ],
    "is_earned": 0,
    "is_dropped": 0
}