{
    "object_id": 14459,
    "components": {
        "2": 14148,
        "11": 7098
    },
    "item_info": {
        "name": "Nic's Test Item for Post Mission Selling",
        "displayName": "Nic's Test Item for Post Mission Selling",
        "type": "Loot",
        "description": "Nic's Test Item for Post Mission Selling",
        "internalNotes": "Nic's Test Item for Post Mission Selling"
    },
    "skills": [],
    "stats": {
        "life": 0,
        "armor": 0,
        "imagination": 0
    },
    "preconditions": {},
    "rarity": 1,
    "is_weapon": 0,
    "is_two_handed": 0,
    "level_requirement": 0,
    "equip_locations": [
        "Consumable"
    ],
    "sell_price": 0,
    "buy_price": 0,
    "alt_currency_type": 0,
    "alt_currency_cost": 0,
    "commendation_currency_type": 0,
    "commendation_currency_cost": 0,
    "stack_size": 50,
    "overview": {},
    "is_sold": 1,
    "vendors": [],
    "is_earned": 0,
    "is_dropped": 0
}