{
    "object_id": 10124,
    "components": {
        "2": 9961,
        "9": 0,
        "11": 4936
    },
    "item_info": {
        "name": "Island Dolphin Shirt",
        "displayName": "Island Dolphin Shirt",
        "type": "Loot",
        "description": "",
        "internalNotes": "1 IP"
    },
    "skills": [],
    "stats": {
        "life": 0,
        "armor": 0,
        "imagination": 1
    },
    "preconditions": {},
    "rarity": 2,
    "is_weapon": 0,
    "is_two_handed": 0,
    "level_requirement": 0,
    "equip_locations": [
        "Torso"
    ],
    "sell_price": 92,
    "buy_price": 925,
    "alt_currency_type": 0,
    "alt_currency_cost": 0,
    "commendation_currency_type": 0,
    "commendation_currency_cost": 0,
    "stack_size": 1,
    "overview": {},
    "is_sold": 0,
    "is_earned": 0,
    "is_dropped": 0
}