{
    "object_id": 6505,
    "components": {
        "2": 6072,
        "11": 2739
    },
    "item_info": {
        "name": "NPC Greeble Cannon Right",
        "displayName": "NPC Greeble Cannon Right",
        "type": "Loot",
        "description": null,
        "internalNotes": "Attach to greeble_r on cannon"
    },
    "skills": [],
    "stats": {
        "life": 0,
        "armor": 0,
        "imagination": 0
    },
    "preconditions": {},
    "rarity": 5,
    "is_weapon": 0,
    "is_two_handed": 0,
    "level_requirement": 0,
    "equip_locations": [
        "Consumable"
    ],
    "sell_price": 0,
    "buy_price": 0,
    "alt_currency_type": 0,
    "alt_currency_cost": 0,
    "commendation_currency_type": 0,
    "commendation_currency_cost": 0,
    "stack_size": 1,
    "overview": {},
    "is_sold": 0,
    "is_earned": 0,
    "is_dropped": 0
}